embedding_lenses/__init__.py
embedding_lenses/app.py
embedding_lenses/data.py
embedding_lenses/dimensionality_reduction.py
embedding_lenses/embedding.py
embedding_lenses/utils.py
embedding_lenses/visualization.py
embedding_lenses-0.11.0.dist-info/LICENSE
embedding_lenses-0.11.0.dist-info/WHEEL
embedding_lenses-0.11.0.dist-info/METADATA
embedding_lenses-0.11.0.dist-info/RECORD
